adspkg/A.py
adspkg/B.py
adspkg/C.py
adspkg/D.py
adspkg/E.py
adspkg/__init__.py
adspkg/hello.py
adspkg/main.py
adspkg-0.0.6.dist-info/METADATA
adspkg-0.0.6.dist-info/WHEEL
adspkg-0.0.6.dist-info/top_level.txt
adspkg-0.0.6.dist-info/RECORD
