Metadata-Version: 2.1
Name: adspkg
Version: 0.0.6
Summary: basic hello pkg
Home-page: UNKNOWN
Author: Mathew Patil
Author-email: UNKNOWN
License: UNKNOWN
Keywords: python,video,stream,video stream,camera stream,sockets
Platform: UNKNOWN
Classifier: Development Status :: 1 - Planning
Classifier: Intended Audience :: Developers
Classifier: Programming Language :: Python :: 3
Classifier: Operating System :: Unix
Classifier: Operating System :: MacOS :: MacOS X
Classifier: Operating System :: Microsoft :: Windows
